checkcert/__init__.py
checkcert/checkcert.py
checkcert-0.7.2.dist-info/entry_points.txt
checkcert-0.7.2.dist-info/WHEEL
checkcert-0.7.2.dist-info/METADATA
checkcert-0.7.2.dist-info/RECORD
