Metadata-Version: 2.1
Name: checkcert
Version: 0.7.2
Summary: CLI to check tls cert information and determine validity
Home-page: https://github.com/kellya/checkcert
License: MIT
Author: Alex Kelly
Author-email: kellya@arachnitech.com
Requires-Python: >=3.9,<4.0
Classifier: License :: OSI Approved :: MIT License
Classifier: Programming Language :: Python :: 3
Classifier: Programming Language :: Python :: 3.10
Classifier: Programming Language :: Python :: 3.9
Requires-Dist: click (>=8.0.1,<9.0.0)
Requires-Dist: pyOpenSSL (>=21.0.0,<22.0.0)
Project-URL: Documentation, https://checkcert.readthedocs.io
